package/__init__.py
package/client.py
facade_sdk-0.4.2.dist-info/METADATA
facade_sdk-0.4.2.dist-info/WHEEL
facade_sdk-0.4.2.dist-info/top_level.txt
facade_sdk-0.4.2.dist-info/RECORD
