Metadata-Version: 2.4
Name: facade-sdk
Version: 0.4.2
Summary: SDK for FACADE system API
Home-page: https://github.com/mseavers1/facade_sdk
Author: Data Team FALL 2025
Classifier: Programming Language :: Python :: 3
Classifier: Operating System :: OS Independent
Requires-Python: >=3.8
Requires-Dist: paho-mqtt>=1.6.1
Dynamic: author
Dynamic: classifier
Dynamic: description
Dynamic: description-content-type
Dynamic: home-page
Dynamic: requires-dist
Dynamic: requires-python
Dynamic: summary
